jwt.py
jwt.py-0.1.0.dist-info/DESCRIPTION.rst
jwt.py-0.1.0.dist-info/top_level.txt
jwt.py-0.1.0.dist-info/METADATA
jwt.py-0.1.0.dist-info/metadata.json
jwt.py-0.1.0.dist-info/WHEEL
jwt.py-0.1.0.dist-info/RECORD
