Metadata-Version: 2.0
Name: jwt.py
Version: 0.1.0
Summary: UNKNOWN
Home-page: https://github.com/iPlantCollaborativeOpenSource/jwt.py
Author: iPlant Collaborative
Author-email: atmodevs@gmail.com
License: UNKNOWN
Platform: UNKNOWN
Requires-Dist: pycrypto (>=2.6)
